[
    {
        "index": "28670",
        "layer": "29-eleuther_gp-res-262k",
        "url": "json/llama3.1-8b-eleuther_gp/mosque/data_for_feature_28670.json",
        "negative_strings": [],
        "positive_strings": [],
        "description": "Places of worship, including synagogues and mosques, and occasionally other related terms such as congregations."
    },
    {
        "index": "104114",
        "layer": "29-eleuther_gp-res-262k",
        "url": "json/llama3.1-8b-eleuther_gp/mosque/data_for_feature_104114.json",
        "negative_strings": [],
        "positive_strings": [],
        "description": "The token \"Mos\" is often found as a prefix in various words, including \"mosque\", \"Moscow\", \"mosquito\", or as part of an adjective or a proper noun, including \"Moses\", \"Mosaic\", and \"Mozart\", often referring to names, places, ethnic groups, or art."
    },
    {
        "index": "137378",
        "layer": "23-eleuther_gp-res-262k",
        "url": "json/llama3.1-8b-eleuther_gp/mosque/data_for_feature_137378.json",
        "negative_strings": [],
        "positive_strings": [],
        "description": "Names of cities or locations, often including the names \"Moscow\", \"Warsaw\", and others, sometimes referencing a specific building or structure such as a mosque."
    },
    {
        "index": "112739",
        "layer": "23-eleuther_gp-res-262k",
        "url": "json/llama3.1-8b-eleuther_gp/mosque/data_for_feature_112739.json",
        "negative_strings": [],
        "positive_strings": [],
        "description": "The word \"mosque\" appears to refer to a building for Islamic worship, while \"synagogue\" refers to a building for Jewish worship, often with a strong sense of community."
    },
    {
        "index": "243161",
        "layer": "29-eleuther_gp-mlp-262k",
        "url": "json/llama3.1-8b-eleuther_gp/mosque/data_for_feature_243161.json",
        "negative_strings": [],
        "positive_strings": [],
        "description": "The token often appears to be part of a proper noun, specifically a place or location, such as a city, mosque, or temple."
    },
    {
        "index": "26632",
        "layer": "23-eleuther_gp-mlp-262k",
        "url": "json/llama3.1-8b-eleuther_gp/mosque/data_for_feature_26632.json",
        "negative_strings": [],
        "positive_strings": [],
        "description": "Geographical names of places and buildings, including mosques, museums, cities, and historical sites, as well as proper nouns related to the Ottoman Empire and Turkish culture."
    },
    {
        "index": "182977",
        "layer": "23-eleuther_gp-mlp-262k",
        "url": "json/llama3.1-8b-eleuther_gp/mosque/data_for_feature_182977.json",
        "negative_strings": [],
        "positive_strings": [],
        "description": "References to religious practices, rituals, and institutions, often involving prayer, worship, or gatherings in places of worship such as mosques, churches, or synagogues."
    },
    {
        "index": "45856",
        "layer": "23-eleuther_gp-mlp-262k",
        "url": "json/llama3.1-8b-eleuther_gp/mosque/data_for_feature_45856.json",
        "negative_strings": [],
        "positive_strings": [],
        "description": "Locations or institutions of worship or organizations affiliated with a particular religion, often including mosques, churches, and schools."
    },
    {
        "index": "206302",
        "layer": "23-eleuther_gp-mlp-262k",
        "url": "json/llama3.1-8b-eleuther_gp/mosque/data_for_feature_206302.json",
        "negative_strings": [],
        "positive_strings": [],
        "description": "Nouns of places or monuments, including museums, castles, islands, palaces, mosques, and other historical sites, often denoting a specific location or tourist attraction."
    },
    {
        "index": "229102",
        "layer": "29-eleuther_gp-res-262k",
        "url": "json/llama3.1-8b-eleuther_gp/mosque/data_for_feature_229102.json",
        "negative_strings": [],
        "positive_strings": [],
        "description": "The token \"mos\" is often found in proper nouns, particularly in names of organizations, people, and products, and is also used in words like \"mosquito\" and \"mosque\"."
    },
    {
        "index": "219140",
        "layer": "29-eleuther_gp-res-262k",
        "url": "json/llama3.1-8b-eleuther_gp/mosque/data_for_feature_219140.json",
        "negative_strings": [],
        "positive_strings": [],
        "description": "A partial or misspelled version of the words \"Moslem\", \"Mosque\", \"Moscow\", or \"Mossad\" that denotes place names, people's names, or names of a particular group, often with a Middle Eastern or Islamic origin."
    },
    {
        "index": "141674",
        "layer": "23-eleuther_gp-res-262k",
        "url": "json/llama3.1-8b-eleuther_gp/mosque/data_for_feature_141674.json",
        "negative_strings": [],
        "positive_strings": [],
        "description": "The token \"mos\" appears to be part of words that are often misspelled or incomplete, particularly in words such as \"mosque\", \"mosquito\", or \"moscow\"."
    }
]