[
    {
        "index": "138795",
        "layer": "23-eleuther_gp-mlp-262k",
        "url": "json/llama3.1-8b-eleuther_gp/Junge/data_for_feature_138795.json",
        "negative_strings": [],
        "positive_strings": [],
        "description": "The text features various examples of short phrases or sentences with a focus on psychology, philosophy, and spirituality, often referencing the works of Carl Jung, and often using colons to introduce or separate items in a series."
    },
    {
        "index": "258479",
        "layer": "23-eleuther_gp-mlp-262k",
        "url": "json/llama3.1-8b-eleuther_gp/Junge/data_for_feature_258479.json",
        "negative_strings": [],
        "positive_strings": [],
        "description": "The text consists of various words, phrases, or parts of words that are mentioned in a psychological or scientific context, often with a focus on human behavior, personality, and development, and are often related to the work of well-known psychologists such as Freud and Jung."
    },
    {
        "index": "47042",
        "layer": "29-eleuther_gp-mlp-262k",
        "url": "json/llama3.1-8b-eleuther_gp/Junge/data_for_feature_47042.json",
        "negative_strings": [],
        "positive_strings": [],
        "description": "Technical terms, concepts, and methods in the field of psychology, particularly psychoanalysis, often referencing Carl Jung."
    },
    {
        "index": "181745",
        "layer": "23-eleuther_gp-res-262k",
        "url": "json/llama3.1-8b-eleuther_gp/Junge/data_for_feature_181745.json",
        "negative_strings": [],
        "positive_strings": [],
        "description": "Proper nouns, often referring to names, particularly of individuals, such as \"Jung\" or \"Jong\", often in the context of titles, quotes, or references to a person's work or actions."
    },
    {
        "index": "136728",
        "layer": "29-eleuther_gp-res-262k",
        "url": "json/llama3.1-8b-eleuther_gp/Junge/data_for_feature_136728.json",
        "negative_strings": [],
        "positive_strings": [],
        "description": "The token is often related to the German surname \"Jung\", and the majority of the instances are associated with Carl Jung, a Swiss psychiatrist and psychoanalyst who founded analytical psychology."
    }
]