[
    {
        "index": "118904",
        "layer": "38-gemmascope-res-131k-l0_32plus",
        "url": "json/gemma-scope/jew/data_for_feature_118904.json",
        "negative_strings": [],
        "positive_strings": [],
        "description": "Words or parts of words starting with the sound /d\u0292u\u02d0/ (often spelled as \"Ju\" or \"Jew\") often representing proper nouns, brand names, or specific references."
    },
    {
        "index": "15693",
        "layer": "39-gemmascope-res-131k-l0_32plus",
        "url": "json/gemma-scope/jew/data_for_feature_15693.json",
        "negative_strings": [],
        "positive_strings": [],
        "description": "References to Jewish or Hebrew culture, identity, or religion, often explicitly mentioning \"Jewish\", \"Judaic\", \"Jew\", \"Hebrew\", \"Torah\", or \"Kosher\"."
    },
    {
        "index": "73128",
        "layer": "41-gemmascope-res-131k-l0_32plus",
        "url": "json/gemma-scope/jew/data_for_feature_73128.json",
        "negative_strings": [],
        "positive_strings": [],
        "description": "Proper nouns related to Jewish culture and identity, such as \"Jewish\", \"Hebrew\", and \"Judaism\", as well as occasional mentions of \"Zionist\" and \"Jews\"."
    },
    {
        "index": "99279",
        "layer": "40-gemmascope-res-131k-l0_32plus",
        "url": "json/gemma-scope/jew/data_for_feature_99279.json",
        "negative_strings": [],
        "positive_strings": [],
        "description": "References to the word 'Jew' or 'Jews', often used in discussions about religion, ethnicity, or cultural identity."
    },
    {
        "index": "53373",
        "layer": "39-gemmascope-res-131k-l0_32plus",
        "url": "json/gemma-scope/jew/data_for_feature_53373.json",
        "negative_strings": [],
        "positive_strings": [],
        "description": "The term \"Jew\" referring to individuals of Jewish faith or ethnicity, often appearing in various contexts such as names, articles, or discussions about Jewish people, culture, or history."
    },
    {
        "index": "29705",
        "layer": "40-gemmascope-res-131k-l0_32plus",
        "url": "json/gemma-scope/jew/data_for_feature_29705.json",
        "negative_strings": [],
        "positive_strings": [],
        "description": "References to Jewish people, culture, or related concepts, often in the context of history, identity, or comparisons with other groups, with \"Jewish\" or \"Jews\" being the most commonly used terms."
    },
    {
        "index": "97598",
        "layer": "40-gemmascope-res-131k",
        "url": "json/gemma-scope/jew/data_for_feature_97598.json",
        "negative_strings": [
            "GEBURTSDATUM",
            "ast\u00e9ro\u00efdes",
            "\u2581nahilalakip",
            "MemoryWarning",
            "\u2581linkovi",
            "\u2581\u0644\u0644\u0627\u0633\u0645\u0627\u0621",
            "\u2581Autorizaciones",
            "SizeF",
            "httphttps",
            "WithIOException"
        ],
        "positive_strings": [
            "ellers",
            "eller",
            "eler",
            "elled",
            "lery",
            "ett",
            "llery",
            "ellery",
            "wery",
            "eleri"
        ],
        "description": " occurrences of the word \"jew\" in various contexts"
    },
    {
        "index": "94010",
        "layer": "41-gemmascope-res-131k-l0_32plus",
        "url": "json/gemma-scope/jew/data_for_feature_94010.json",
        "negative_strings": [],
        "positive_strings": [],
        "description": "References to Jews, Judaism, and related words, often in contexts discussing religion, ethnicity, or cultural identity."
    },
    {
        "index": "98473",
        "layer": "36-gemmascope-res-131k-l0_32plus",
        "url": "json/gemma-scope/jew/data_for_feature_98473.json",
        "negative_strings": [],
        "positive_strings": [],
        "description": "References to Jewish identity, culture, or artifacts, often denoted by the words \"Jew\", \"Jewish\", \"Judaic\", or \"jewelry\", as well as phrases or words that are specifically associated with Jewish culture or tradition."
    },
    {
        "index": "92732",
        "layer": "32-gemmascope-res-131k-l0_32plus",
        "url": "json/gemma-scope/jew/data_for_feature_92732.json",
        "negative_strings": [],
        "positive_strings": [],
        "description": "The token \"Jew\" and its variations, often being used as a noun or part of a phrase referencing Jewish identity or a person of Jewish faith."
    },
    {
        "index": "54342",
        "layer": "20-gemmascope-res-65k",
        "url": "json/gemma-scope/jew/data_for_feature_54342.json",
        "negative_strings": [
            "\u811a\u6ce8\u306e\u4f7f\u3044\u65b9",
            "Personendaten",
            "oredCriteria",
            "\u2581\u0938\u092e\u0940\u0915\u094d\u0937\u093e\u0913\u0902",
            "\u53d1\u8868\u4e8e",
            "\u2581\u062a\u0636\u064a\u0641\u0644\u0647\u0627",
            "\u2581\u0432\u0438\u043f\u0440\u0430\u0432\u0438\u0432\u0448\u0438",
            "UnusedPrivate",
            "\u2581insuffisamment",
            "\u2581FishBase"
        ],
        "positive_strings": [
            "\u2581Je",
            "\u2581Jez",
            "Je",
            "\u2581suis",
            "\u2581je",
            "je",
            "JEE",
            "fortawesome",
            "FFER",
            "jeje"
        ],
        "description": " references to individuals or groups, specifically those with the name \"Jew.\""
    },
    {
        "index": "19094",
        "layer": "41-gemmascope-res-131k",
        "url": "json/gemma-scope/jew/data_for_feature_19094.json",
        "negative_strings": [
            "qrstuvwxyz",
            "\u2581CHtml",
            "ExecuteReader",
            "RegressionTest",
            "\u2581taco",
            "\u2581Unwin",
            "Taco",
            "\u2581\u0627\u0644\u0627\u0637\u0644\u0627\u0639",
            "\u304b\u308a",
            "omitempty"
        ],
        "positive_strings": [
            "\u2581Zagreb",
            "\u2581Croatian",
            "\u2581Croatia",
            "\u2581Hrvats",
            "Croatia",
            "\u2581Split",
            "Cro",
            "\u2581Osi",
            "\u2581cro",
            "\u2581Cro"
        ],
        "description": " references to the historical events and conditions surrounding the Holocaust, particularly focusing on the deportation and murder of Jews"
    },
    {
        "index": "118249",
        "layer": "33-gemmascope-res-131k-l0_32plus",
        "url": "json/gemma-scope/jew/data_for_feature_118249.json",
        "negative_strings": [],
        "positive_strings": [],
        "description": "The token often seems to represent a word related to the term \"jewel\", \"jew\" or other similar words such as \"jelly\", \"jem\", \"jewelry\", \"jewish\", \"jewish\", \"jewels\" indicating that the token may be part of proper noun or identifying specific cultural backgrounds."
    },
    {
        "index": "8193",
        "layer": "35-gemmascope-res-131k",
        "url": "json/gemma-scope/jew/data_for_feature_8193.json",
        "negative_strings": [
            "GEBURTSDATUM",
            "oredCriteria",
            "ftagPool",
            "GeoNames",
            "ast\u00e9ro\u00efdes",
            "Insee",
            "\u2581Roskov",
            "Carriera",
            "routeProvider",
            "Marshal"
        ],
        "positive_strings": [
            "Jew",
            "\u2581Jew",
            "eler",
            "\u2581Jewel",
            "\u2581jew",
            "\u2581Jewell",
            "\u2581jewel",
            "\u2581jewelry",
            "\u2581Jewels",
            "ellers"
        ],
        "description": " mentions of the term \"Jew\" and its variations"
    },
    {
        "index": "78706",
        "layer": "40-gemmascope-res-131k",
        "url": "json/gemma-scope/jew/data_for_feature_78706.json",
        "negative_strings": [
            "\u2581CHtml",
            "calipsis",
            "RegressionTest",
            "ExecuteReader",
            "chargement",
            "\u2581Kyrgyz",
            "delwed",
            "qrstuvwxyz",
            "\u2581modelAndView",
            "\u2581Selective"
        ],
        "positive_strings": [
            "\u2581Croatian",
            "\u2581Zagreb",
            "\u2581Croatia",
            "Cro",
            "Croatia",
            "\u2581Cro",
            "\u2581Hrvats",
            "\u2581cro",
            "\u2581HRT",
            "Personensuche"
        ],
        "description": "references to historical events related to the massacre and persecution of Jews during wartime"
    },
    {
        "index": "2063",
        "layer": "40-gemmascope-res-16k",
        "url": "json/gemma-scope/jew/data_for_feature_2063.json",
        "negative_strings": [
            "\u2581CHtml",
            "\u2581load",
            "\u2581chalk",
            "bindingNavigator",
            "\u2581Leicester",
            "N\u00e9pess\u00e9g",
            "\u2581Unwin",
            "compens",
            "load",
            "\u2581Wichita"
        ],
        "positive_strings": [
            "OGND",
            "\u2581Croatian",
            "\u2581Croatia",
            "Croatia",
            "\u2581Split",
            "\u2581Zagreb",
            "\u2581Hrvats",
            "Split",
            "Cro",
            "\u2581Cro"
        ],
        "description": "references to the historical persecution and violence against Jews during the Holocaust"
    },
    {
        "index": "54310",
        "layer": "40-gemmascope-res-131k",
        "url": "json/gemma-scope/jew/data_for_feature_54310.json",
        "negative_strings": [
            "rungsseite",
            "\u2581Lokales",
            "\u2581\u043d\u0435\u0437\u0430\u0432\u0435\u0440\u0448\u0435\u043d\u0430",
            "djangoproject",
            "LookAnd",
            "\u2581ujednoznacz",
            "R\u00fcyada",
            "FunctionFlags",
            "\u2581\u0645\u0634\u064a\u0646",
            "bootstrapcdn"
        ],
        "positive_strings": [
            "\u2581rounded",
            "\u2581rounding",
            "\u2581Rounded",
            "\u2581shipped",
            "rounded",
            "\u2581round",
            "\u2581Round",
            "\u2581deported",
            "\u2581ROUND",
            "\u2581roundup"
        ],
        "description": "references to historical persecution and violence, particularly against Jews and other marginalized groups"
    },
    {
        "index": "528",
        "layer": "30-gemmascope-res-16k-l0_32plus",
        "url": "json/gemma-scope/jew/data_for_feature_528.json",
        "negative_strings": [
            "\u00e9valuateur",
            "windowFixed",
            "\u2581manteau",
            "BagLayout",
            "\u2581espoir",
            "\u2581variante",
            "\u2581esp\u00e9",
            "\u2581tetapi",
            "\u2581Sure",
            "\u2581Schon"
        ],
        "positive_strings": [
            "\u2581having",
            "\u2581being",
            "\u2581needing",
            "\u2581doing",
            "\u2581looking",
            "\u2581behaving",
            "\u2581embro",
            "\u2581getting",
            "being",
            "\u2581wanting"
        ],
        "description": "Words describing movement, progression, or location (\"up\" \"in\" \"out\" \"back\" \"there\" \"to\"), reflexive pronouns (\"myself\" \"himself\"), or nouns denoting entities that are in some state or position (\"me\" \"us\" \"them\" \"Jews\")."
    },
    {
        "index": "33022",
        "layer": "35-gemmascope-res-131k-l0_32plus",
        "url": "json/gemma-scope/jew/data_for_feature_33022.json",
        "negative_strings": [],
        "positive_strings": [],
        "description": "Phrases associated with the Holocaust, World War II, and Nazi Germany, often referencing concentration camps, the persecution of Jews, and notable figures from that time period."
    },
    {
        "index": "7059",
        "layer": "34-gemmascope-res-16k",
        "url": "json/gemma-scope/jew/data_for_feature_7059.json",
        "negative_strings": [
            "V\u00e4lislingid",
            "\u2581Moli\u00e8re",
            "Spolja\u0161nje",
            "Carriera",
            "\u0645\u0635\u0627\u062f\u0631",
            "\u0411\u0438\u043b\u0433\u0430\u043b\u0434\u0430\u0445\u0430\u0440\u0448",
            "orteur",
            "\u2581fonder",
            "AutoScale",
            "\u2581Sumo"
        ],
        "positive_strings": [
            "\u2581prophe",
            "\u2581prophecies",
            "\u2581prophecy",
            "\u2581Prophecy",
            "\u2581foretold",
            "\u2581predicted",
            "Judgment",
            "\u2581prophetic",
            "\u2581fulfillment",
            "\u2581Prophe"
        ],
        "description": "references to conspiracy theories involving Jews and financial control"
    }
]